CodeEditor/__init__.py
CodeEditor/auxilary.py
CodeEditor/editor.py
CodeEditor/lang.py
CodeEditor/search.py
CodeEditor/setting_enums.py
CodeEditor/settings.py
CodeEditor/lexers/__init__.py
CodeEditor/lexers/lexer_qss.py
CodeEditor/lexers/lexer_text.py
CodeEditor-1.1.0.dist-info/LICENSE
CodeEditor-1.1.0.dist-info/METADATA
CodeEditor-1.1.0.dist-info/WHEEL
CodeEditor-1.1.0.dist-info/top_level.txt
CodeEditor-1.1.0.dist-info/RECORD
