Metadata-Version: 2.1
Name: CodeEditor
Version: 1.1.0
Summary: UNKNOWN
Home-page: https://github.com/hustlei/CodeEditor
Author: lileilei
Author-email: hustlei@sina.cn
License: UNKNOWN
Project-URL: Source Code, https://github.com/hustlei/CodeEditor
Keywords: editor highlight
Platform: UNKNOWN
Classifier: License :: OSI Approved :: GNU Lesser General Public License v3 or later (LGPLv3+)
Classifier: Programming Language :: Python :: 3
Classifier: Operating System :: OS Independent
Requires-Dist: chardet
Requires-Dist: Qscintilla
